{
  "schema_version": 1,
  "topic_id": "137",
  "topic_title": "Distributing the Negative Sign in a Linear Expression",
  "source_html": "/home/jake/Developer/MA/DATA/Topic-HTML/137.html",
  "source_url": "https://mathacademy.com/topics/137",
  "toc": {
    "sidebar_selector": "#sidebar",
    "section_links_selector": "#sectionLinks .sectionLink",
    "section_links": [
      {
        "index": 1,
        "step_id": "2759",
        "dom_id": "sectionLink-2759",
        "name": "",
        "title": "Introduction",
        "selector": "#sectionLink-2759"
      },
      {
        "index": 2,
        "step_id": "5140",
        "dom_id": "sectionLink-5140",
        "name": "",
        "title": "Distributing the Negative Sign over the Sum of Two Terms",
        "selector": "#sectionLink-5140"
      },
      {
        "index": 3,
        "step_id": "2760",
        "dom_id": "sectionLink-2760",
        "name": "",
        "title": "Distributing the Negative Sign over the Difference of Two Terms",
        "selector": "#sectionLink-2760"
      },
      {
        "index": 4,
        "step_id": "2766",
        "dom_id": "sectionLink-2766",
        "name": "",
        "title": "Rule of Thumb",
        "selector": "#sectionLink-2766"
      },
      {
        "index": 5,
        "step_id": "4896",
        "dom_id": "sectionLink-4896",
        "name": "",
        "title": "Distributing the Negative over More Than Two Terms",
        "selector": "#sectionLink-4896"
      }
    ],
    "topic_prerequisites": [
      {
        "topic_id": "3847",
        "name": "The Distributive Law With Three Terms",
        "href": "/topics/the-distributive-law-with-three-terms-3847"
      }
    ]
  },
  "lesson": {
    "container_selector": "#lessonContent",
    "item_count": 11,
    "items": [
      {
        "index": 1,
        "item_type": "step",
        "step_type": "tutorial",
        "step_id": "2759",
        "content_id": "1357",
        "dom_id": "step-2759",
        "selector": "#step-2759",
        "step_anchor": "step-1",
        "title": "Introduction",
        "key_prerequisites": [],
        "has_content_in_snapshot": true
      },
      {
        "index": 2,
        "item_type": "step",
        "step_type": "example",
        "step_id": "5140",
        "content_id": "1601",
        "dom_id": "step-5140",
        "selector": "#step-5140",
        "step_anchor": "step-2",
        "title": "Distributing the Negative Sign over the Sum of Two Terms",
        "key_prerequisites": [
          {
            "topic_id": "135",
            "name": "Applying the Distributive Law With Linear Expressions",
            "href": "/topics/135"
          },
          {
            "topic_id": "298",
            "name": "Multiplying Positive Numbers With Negative Numbers",
            "href": "/topics/298"
          }
        ],
        "has_content_in_snapshot": true
      },
      {
        "index": 3,
        "item_type": "question",
        "question_id": "315",
        "dom_id": "question-315",
        "selector": "#question-315",
        "title": "",
        "has_content_in_snapshot": false,
        "hydration_required": true,
        "question_format": "unknown",
        "choice_count": 0
      },
      {
        "index": 4,
        "item_type": "question",
        "question_id": "57028",
        "dom_id": "question-57028",
        "selector": "#question-57028",
        "title": "",
        "has_content_in_snapshot": false,
        "hydration_required": true,
        "question_format": "unknown",
        "choice_count": 0
      },
      {
        "index": 5,
        "item_type": "step",
        "step_type": "example",
        "step_id": "2760",
        "content_id": "809",
        "dom_id": "step-2760",
        "selector": "#step-2760",
        "step_anchor": "step-5",
        "title": "Distributing the Negative Sign over the Difference of Two Terms",
        "key_prerequisites": [],
        "has_content_in_snapshot": true
      },
      {
        "index": 6,
        "item_type": "question",
        "question_id": "2259",
        "dom_id": "question-2259",
        "selector": "#question-2259",
        "title": "",
        "has_content_in_snapshot": false,
        "hydration_required": true,
        "question_format": "unknown",
        "choice_count": 0
      },
      {
        "index": 7,
        "item_type": "question",
        "question_id": "57029",
        "dom_id": "question-57029",
        "selector": "#question-57029",
        "title": "",
        "has_content_in_snapshot": false,
        "hydration_required": true,
        "question_format": "unknown",
        "choice_count": 0
      },
      {
        "index": 8,
        "item_type": "step",
        "step_type": "tutorial",
        "step_id": "2766",
        "content_id": "1358",
        "dom_id": "step-2766",
        "selector": "#step-2766",
        "step_anchor": "step-8",
        "title": "Rule of Thumb",
        "key_prerequisites": [],
        "has_content_in_snapshot": true
      },
      {
        "index": 9,
        "item_type": "step",
        "step_type": "example",
        "step_id": "4896",
        "content_id": "1540",
        "dom_id": "step-4896",
        "selector": "#step-4896",
        "step_anchor": "step-9",
        "title": "Distributing the Negative over More Than Two Terms",
        "key_prerequisites": [
          {
            "topic_id": "3847",
            "name": "The Distributive Law With Three Terms",
            "href": "/topics/3847"
          }
        ],
        "has_content_in_snapshot": true
      },
      {
        "index": 10,
        "item_type": "question",
        "question_id": "3195",
        "dom_id": "question-3195",
        "selector": "#question-3195",
        "title": "",
        "has_content_in_snapshot": false,
        "hydration_required": true,
        "question_format": "unknown",
        "choice_count": 0
      },
      {
        "index": 11,
        "item_type": "question",
        "question_id": "3187",
        "dom_id": "question-3187",
        "selector": "#question-3187",
        "title": "",
        "has_content_in_snapshot": false,
        "hydration_required": true,
        "question_format": "unknown",
        "choice_count": 0
      }
    ]
  },
  "capture_targets": {
    "toc": {
      "selector": "#sidebar",
      "filename": "00-TOC.png"
    },
    "lesson_items": [
      {
        "index": 1,
        "item_type": "step",
        "selector": "#step-2759",
        "filename": "01-step-2759.png"
      },
      {
        "index": 2,
        "item_type": "step",
        "selector": "#step-5140",
        "filename": "02-step-5140.png"
      },
      {
        "index": 3,
        "item_type": "question",
        "selector": "#question-315",
        "filename": "03-question-315.png"
      },
      {
        "index": 4,
        "item_type": "question",
        "selector": "#question-57028",
        "filename": "04-question-57028.png"
      },
      {
        "index": 5,
        "item_type": "step",
        "selector": "#step-2760",
        "filename": "05-step-2760.png"
      },
      {
        "index": 6,
        "item_type": "question",
        "selector": "#question-2259",
        "filename": "06-question-2259.png"
      },
      {
        "index": 7,
        "item_type": "question",
        "selector": "#question-57029",
        "filename": "07-question-57029.png"
      },
      {
        "index": 8,
        "item_type": "step",
        "selector": "#step-2766",
        "filename": "08-step-2766.png"
      },
      {
        "index": 9,
        "item_type": "step",
        "selector": "#step-4896",
        "filename": "09-step-4896.png"
      },
      {
        "index": 10,
        "item_type": "question",
        "selector": "#question-3195",
        "filename": "10-question-3195.png"
      },
      {
        "index": 11,
        "item_type": "question",
        "selector": "#question-3187",
        "filename": "11-question-3187.png"
      }
    ]
  }
}
