{
  "schema_version": 1,
  "topic_id": "1995",
  "topic_title": "Surface Areas of Revolution for Parametric Curves",
  "source_html": "/home/jake/Developer/MA/DATA/Topic-HTML/1995.html",
  "source_url": "https://mathacademy.com/topics/1995",
  "toc": {
    "sidebar_selector": "#sidebar",
    "section_links_selector": "#sectionLinks .sectionLink",
    "section_links": [
      {
        "index": 1,
        "step_id": "37129",
        "dom_id": "sectionLink-37129",
        "name": "",
        "title": "Introduction",
        "selector": "#sectionLink-37129"
      },
      {
        "index": 2,
        "step_id": "44711",
        "dom_id": "sectionLink-44711",
        "name": "",
        "title": "A Worked Example",
        "selector": "#sectionLink-44711"
      },
      {
        "index": 3,
        "step_id": "37127",
        "dom_id": "sectionLink-37127",
        "name": "",
        "title": "Integrals Representing Surface Areas Generated by Functions of X",
        "selector": "#sectionLink-37127"
      },
      {
        "index": 4,
        "step_id": "37307",
        "dom_id": "sectionLink-37307",
        "name": "",
        "title": "Surface Area Generated by Functions of Y",
        "selector": "#sectionLink-37307"
      },
      {
        "index": 5,
        "step_id": "37128",
        "dom_id": "sectionLink-37128",
        "name": "",
        "title": "Integrals Representing Surface Areas Generated by Functions of Y",
        "selector": "#sectionLink-37128"
      },
      {
        "index": 6,
        "step_id": "37135",
        "dom_id": "sectionLink-37135",
        "name": "",
        "title": "Computing a Surface Area of Revolution",
        "selector": "#sectionLink-37135"
      }
    ],
    "topic_prerequisites": [
      {
        "topic_id": "997",
        "name": "The Arc Length of a Parametric Curve",
        "href": "/topics/the-arc-length-of-a-parametric-curve-997"
      },
      {
        "topic_id": "3632",
        "name": "Surface Areas of Revolution: Rotation About the Y-Axis",
        "href": "/topics/surface-areas-of-revolution-rotation-about-the-y-axis-3632"
      }
    ]
  },
  "lesson": {
    "container_selector": "#lessonContent",
    "item_count": 12,
    "items": [
      {
        "index": 1,
        "item_type": "step",
        "step_type": "tutorial",
        "step_id": "37129",
        "content_id": "6113",
        "dom_id": "step-37129",
        "selector": "#step-37129",
        "step_anchor": "step-1",
        "title": "Introduction",
        "key_prerequisites": [],
        "has_content_in_snapshot": true
      },
      {
        "index": 2,
        "item_type": "step",
        "step_type": "tutorial",
        "step_id": "44711",
        "content_id": "7707",
        "dom_id": "step-44711",
        "selector": "#step-44711",
        "step_anchor": "step-2",
        "title": "A Worked Example",
        "key_prerequisites": [],
        "has_content_in_snapshot": true
      },
      {
        "index": 3,
        "item_type": "step",
        "step_type": "example",
        "step_id": "37127",
        "content_id": "9866",
        "dom_id": "step-37127",
        "selector": "#step-37127",
        "step_anchor": "step-3",
        "title": "Integrals Representing Surface Areas Generated by Functions of X",
        "key_prerequisites": [
          {
            "topic_id": "997",
            "name": "The Arc Length of a Parametric Curve",
            "href": "/topics/997"
          },
          {
            "topic_id": "1994",
            "name": "Surface Areas of Revolution: Rotation About the X-Axis",
            "href": "/topics/1994"
          }
        ],
        "has_content_in_snapshot": true
      },
      {
        "index": 4,
        "item_type": "question",
        "question_id": "139069",
        "dom_id": "question-139069",
        "selector": "#question-139069",
        "title": "",
        "has_content_in_snapshot": false,
        "hydration_required": true,
        "question_format": "unknown",
        "choice_count": 0
      },
      {
        "index": 5,
        "item_type": "question",
        "question_id": "138944",
        "dom_id": "question-138944",
        "selector": "#question-138944",
        "title": "",
        "has_content_in_snapshot": false,
        "hydration_required": true,
        "question_format": "unknown",
        "choice_count": 0
      },
      {
        "index": 6,
        "item_type": "step",
        "step_type": "tutorial",
        "step_id": "37307",
        "content_id": "6145",
        "dom_id": "step-37307",
        "selector": "#step-37307",
        "step_anchor": "step-6",
        "title": "Surface Area Generated by Functions of Y",
        "key_prerequisites": [],
        "has_content_in_snapshot": true
      },
      {
        "index": 7,
        "item_type": "step",
        "step_type": "example",
        "step_id": "37128",
        "content_id": "9867",
        "dom_id": "step-37128",
        "selector": "#step-37128",
        "step_anchor": "step-7",
        "title": "Integrals Representing Surface Areas Generated by Functions of Y",
        "key_prerequisites": [
          {
            "topic_id": "3632",
            "name": "Surface Areas of Revolution: Rotation About the Y-Axis",
            "href": "/topics/3632"
          }
        ],
        "has_content_in_snapshot": true
      },
      {
        "index": 8,
        "item_type": "question",
        "question_id": "138945",
        "dom_id": "question-138945",
        "selector": "#question-138945",
        "title": "",
        "has_content_in_snapshot": false,
        "hydration_required": true,
        "question_format": "unknown",
        "choice_count": 0
      },
      {
        "index": 9,
        "item_type": "question",
        "question_id": "138981",
        "dom_id": "question-138981",
        "selector": "#question-138981",
        "title": "",
        "has_content_in_snapshot": false,
        "hydration_required": true,
        "question_format": "unknown",
        "choice_count": 0
      },
      {
        "index": 10,
        "item_type": "step",
        "step_type": "example",
        "step_id": "37135",
        "content_id": "9869",
        "dom_id": "step-37135",
        "selector": "#step-37135",
        "step_anchor": "step-10",
        "title": "Computing a Surface Area of Revolution",
        "key_prerequisites": [],
        "has_content_in_snapshot": true
      },
      {
        "index": 11,
        "item_type": "question",
        "question_id": "138970",
        "dom_id": "question-138970",
        "selector": "#question-138970",
        "title": "",
        "has_content_in_snapshot": false,
        "hydration_required": true,
        "question_format": "unknown",
        "choice_count": 0
      },
      {
        "index": 12,
        "item_type": "question",
        "question_id": "138946",
        "dom_id": "question-138946",
        "selector": "#question-138946",
        "title": "",
        "has_content_in_snapshot": false,
        "hydration_required": true,
        "question_format": "unknown",
        "choice_count": 0
      }
    ]
  },
  "capture_targets": {
    "toc": {
      "selector": "#sidebar",
      "filename": "00-TOC.png"
    },
    "lesson_items": [
      {
        "index": 1,
        "item_type": "step",
        "selector": "#step-37129",
        "filename": "01-step-37129.png"
      },
      {
        "index": 2,
        "item_type": "step",
        "selector": "#step-44711",
        "filename": "02-step-44711.png"
      },
      {
        "index": 3,
        "item_type": "step",
        "selector": "#step-37127",
        "filename": "03-step-37127.png"
      },
      {
        "index": 4,
        "item_type": "question",
        "selector": "#question-139069",
        "filename": "04-question-139069.png"
      },
      {
        "index": 5,
        "item_type": "question",
        "selector": "#question-138944",
        "filename": "05-question-138944.png"
      },
      {
        "index": 6,
        "item_type": "step",
        "selector": "#step-37307",
        "filename": "06-step-37307.png"
      },
      {
        "index": 7,
        "item_type": "step",
        "selector": "#step-37128",
        "filename": "07-step-37128.png"
      },
      {
        "index": 8,
        "item_type": "question",
        "selector": "#question-138945",
        "filename": "08-question-138945.png"
      },
      {
        "index": 9,
        "item_type": "question",
        "selector": "#question-138981",
        "filename": "09-question-138981.png"
      },
      {
        "index": 10,
        "item_type": "step",
        "selector": "#step-37135",
        "filename": "10-step-37135.png"
      },
      {
        "index": 11,
        "item_type": "question",
        "selector": "#question-138970",
        "filename": "11-question-138970.png"
      },
      {
        "index": 12,
        "item_type": "question",
        "selector": "#question-138946",
        "filename": "12-question-138946.png"
      }
    ]
  }
}
