{
  "schema_version": 1,
  "topic_id": "227",
  "topic_title": "Dividing Complex Numbers",
  "source_html": "/home/jake/Developer/MA/DATA/Topic-HTML/227.html",
  "source_url": "https://mathacademy.com/topics/227",
  "toc": {
    "sidebar_selector": "#sidebar",
    "section_links_selector": "#sectionLinks .sectionLink",
    "section_links": [
      {
        "index": 1,
        "step_id": "20984",
        "dom_id": "sectionLink-20984",
        "name": "",
        "title": "Introduction",
        "selector": "#sectionLink-20984"
      },
      {
        "index": 2,
        "step_id": "20986",
        "dom_id": "sectionLink-20986",
        "name": "",
        "title": "Dividing Two Complex Numbers",
        "selector": "#sectionLink-20986"
      },
      {
        "index": 3,
        "step_id": "23323",
        "dom_id": "sectionLink-23323",
        "name": "",
        "title": "Dividing an Imaginary Number by a Complex Number",
        "selector": "#sectionLink-23323"
      },
      {
        "index": 4,
        "step_id": "23324",
        "dom_id": "sectionLink-23324",
        "name": "",
        "title": "Dividing a Real Number by a Complex Number",
        "selector": "#sectionLink-23324"
      },
      {
        "index": 5,
        "step_id": "20987",
        "dom_id": "sectionLink-20987",
        "name": "",
        "title": "Dividing a Complex Number by an Imaginary Number",
        "selector": "#sectionLink-20987"
      }
    ],
    "topic_prerequisites": [
      {
        "topic_id": "905",
        "name": "Special Properties of the Complex Conjugate",
        "href": "/topics/special-properties-of-the-complex-conjugate-905"
      }
    ]
  },
  "lesson": {
    "container_selector": "#lessonContent",
    "item_count": 13,
    "items": [
      {
        "index": 1,
        "item_type": "step",
        "step_type": "tutorial",
        "step_id": "20984",
        "content_id": "3735",
        "dom_id": "step-20984",
        "selector": "#step-20984",
        "step_anchor": "step-1",
        "title": "Introduction",
        "key_prerequisites": [],
        "has_content_in_snapshot": true
      },
      {
        "index": 2,
        "item_type": "step",
        "step_type": "example",
        "step_id": "20986",
        "content_id": "5780",
        "dom_id": "step-20986",
        "selector": "#step-20986",
        "step_anchor": "step-2",
        "title": "Dividing Two Complex Numbers",
        "key_prerequisites": [
          {
            "topic_id": "33",
            "name": "Multiplying Complex Numbers",
            "href": "/topics/33"
          },
          {
            "topic_id": "905",
            "name": "Special Properties of the Complex Conjugate",
            "href": "/topics/905"
          }
        ],
        "has_content_in_snapshot": true
      },
      {
        "index": 3,
        "item_type": "question",
        "question_id": "939",
        "dom_id": "question-939",
        "selector": "#question-939",
        "title": "",
        "has_content_in_snapshot": false,
        "hydration_required": true,
        "question_format": "unknown",
        "choice_count": 0
      },
      {
        "index": 4,
        "item_type": "question",
        "question_id": "964",
        "dom_id": "question-964",
        "selector": "#question-964",
        "title": "",
        "has_content_in_snapshot": false,
        "hydration_required": true,
        "question_format": "unknown",
        "choice_count": 0
      },
      {
        "index": 5,
        "item_type": "step",
        "step_type": "example",
        "step_id": "23323",
        "content_id": "6230",
        "dom_id": "step-23323",
        "selector": "#step-23323",
        "step_anchor": "step-5",
        "title": "Dividing an Imaginary Number by a Complex Number",
        "key_prerequisites": [],
        "has_content_in_snapshot": true
      },
      {
        "index": 6,
        "item_type": "question",
        "question_id": "16434",
        "dom_id": "question-16434",
        "selector": "#question-16434",
        "title": "",
        "has_content_in_snapshot": false,
        "hydration_required": true,
        "question_format": "unknown",
        "choice_count": 0
      },
      {
        "index": 7,
        "item_type": "question",
        "question_id": "963",
        "dom_id": "question-963",
        "selector": "#question-963",
        "title": "",
        "has_content_in_snapshot": false,
        "hydration_required": true,
        "question_format": "unknown",
        "choice_count": 0
      },
      {
        "index": 8,
        "item_type": "step",
        "step_type": "example",
        "step_id": "23324",
        "content_id": "6231",
        "dom_id": "step-23324",
        "selector": "#step-23324",
        "step_anchor": "step-8",
        "title": "Dividing a Real Number by a Complex Number",
        "key_prerequisites": [],
        "has_content_in_snapshot": true
      },
      {
        "index": 9,
        "item_type": "question",
        "question_id": "16435",
        "dom_id": "question-16435",
        "selector": "#question-16435",
        "title": "",
        "has_content_in_snapshot": false,
        "hydration_required": true,
        "question_format": "unknown",
        "choice_count": 0
      },
      {
        "index": 10,
        "item_type": "question",
        "question_id": "541",
        "dom_id": "question-541",
        "selector": "#question-541",
        "title": "",
        "has_content_in_snapshot": false,
        "hydration_required": true,
        "question_format": "unknown",
        "choice_count": 0
      },
      {
        "index": 11,
        "item_type": "step",
        "step_type": "example",
        "step_id": "20987",
        "content_id": "5781",
        "dom_id": "step-20987",
        "selector": "#step-20987",
        "step_anchor": "step-11",
        "title": "Dividing a Complex Number by an Imaginary Number",
        "key_prerequisites": [],
        "has_content_in_snapshot": true
      },
      {
        "index": 12,
        "item_type": "question",
        "question_id": "965",
        "dom_id": "question-965",
        "selector": "#question-965",
        "title": "",
        "has_content_in_snapshot": false,
        "hydration_required": true,
        "question_format": "unknown",
        "choice_count": 0
      },
      {
        "index": 13,
        "item_type": "question",
        "question_id": "74363",
        "dom_id": "question-74363",
        "selector": "#question-74363",
        "title": "",
        "has_content_in_snapshot": false,
        "hydration_required": true,
        "question_format": "unknown",
        "choice_count": 0
      }
    ]
  },
  "capture_targets": {
    "toc": {
      "selector": "#sidebar",
      "filename": "00-TOC.png"
    },
    "lesson_items": [
      {
        "index": 1,
        "item_type": "step",
        "selector": "#step-20984",
        "filename": "01-step-20984.png"
      },
      {
        "index": 2,
        "item_type": "step",
        "selector": "#step-20986",
        "filename": "02-step-20986.png"
      },
      {
        "index": 3,
        "item_type": "question",
        "selector": "#question-939",
        "filename": "03-question-939.png"
      },
      {
        "index": 4,
        "item_type": "question",
        "selector": "#question-964",
        "filename": "04-question-964.png"
      },
      {
        "index": 5,
        "item_type": "step",
        "selector": "#step-23323",
        "filename": "05-step-23323.png"
      },
      {
        "index": 6,
        "item_type": "question",
        "selector": "#question-16434",
        "filename": "06-question-16434.png"
      },
      {
        "index": 7,
        "item_type": "question",
        "selector": "#question-963",
        "filename": "07-question-963.png"
      },
      {
        "index": 8,
        "item_type": "step",
        "selector": "#step-23324",
        "filename": "08-step-23324.png"
      },
      {
        "index": 9,
        "item_type": "question",
        "selector": "#question-16435",
        "filename": "09-question-16435.png"
      },
      {
        "index": 10,
        "item_type": "question",
        "selector": "#question-541",
        "filename": "10-question-541.png"
      },
      {
        "index": 11,
        "item_type": "step",
        "selector": "#step-20987",
        "filename": "11-step-20987.png"
      },
      {
        "index": 12,
        "item_type": "question",
        "selector": "#question-965",
        "filename": "12-question-965.png"
      },
      {
        "index": 13,
        "item_type": "question",
        "selector": "#question-74363",
        "filename": "13-question-74363.png"
      }
    ]
  }
}
