{
  "schema_version": 1,
  "topic_id": "269",
  "topic_title": "Finding Trigonometric Ratios of Quadrantal Angles",
  "source_html": "/home/jake/Developer/MA/DATA/Topic-HTML/269.html",
  "source_url": "https://mathacademy.com/topics/269",
  "toc": {
    "sidebar_selector": "#sidebar",
    "section_links_selector": "#sectionLinks .sectionLink",
    "section_links": [
      {
        "index": 1,
        "step_id": "453667",
        "dom_id": "sectionLink-453667",
        "name": "",
        "title": "Introduction",
        "selector": "#sectionLink-453667"
      },
      {
        "index": 2,
        "step_id": "453668",
        "dom_id": "sectionLink-453668",
        "name": "",
        "title": "Computing the Sine or Cosine of a Quadrantal Angle",
        "selector": "#sectionLink-453668"
      },
      {
        "index": 3,
        "step_id": "453671",
        "dom_id": "sectionLink-453671",
        "name": "",
        "title": "Computing the Tangent or Cotangent of a Quadrantal Angle",
        "selector": "#sectionLink-453671"
      },
      {
        "index": 4,
        "step_id": "453675",
        "dom_id": "sectionLink-453675",
        "name": "",
        "title": "Computing a Reciprocal Ratio of a Quadrantal Angle",
        "selector": "#sectionLink-453675"
      }
    ],
    "topic_prerequisites": [
      {
        "topic_id": "4037",
        "name": "Extending the Trigonometric Ratios Using Angles in Radians",
        "href": "/topics/extending-the-trigonometric-ratios-using-angles-in-radians-4037"
      }
    ]
  },
  "lesson": {
    "container_selector": "#lessonContent",
    "item_count": 11,
    "items": [
      {
        "index": 1,
        "item_type": "step",
        "step_type": "tutorial",
        "step_id": "453667",
        "content_id": "2723",
        "dom_id": "step-453667",
        "selector": "#step-453667",
        "step_anchor": "step-1",
        "title": "Introduction",
        "key_prerequisites": [],
        "has_content_in_snapshot": true
      },
      {
        "index": 2,
        "item_type": "step",
        "step_type": "example",
        "step_id": "453668",
        "content_id": "3863",
        "dom_id": "step-453668",
        "selector": "#step-453668",
        "step_anchor": "step-2",
        "title": "Computing the Sine or Cosine of a Quadrantal Angle",
        "key_prerequisites": [
          {
            "topic_id": "112",
            "name": "Properties of the Unit Circle in the First Quadrant",
            "href": "/topics/112"
          }
        ],
        "has_content_in_snapshot": true
      },
      {
        "index": 3,
        "item_type": "question",
        "question_id": "262318",
        "dom_id": "question-262318",
        "selector": "#question-262318",
        "title": "",
        "has_content_in_snapshot": false,
        "hydration_required": true,
        "question_format": "unknown",
        "choice_count": 0
      },
      {
        "index": 4,
        "item_type": "question",
        "question_id": "1699",
        "dom_id": "question-1699",
        "selector": "#question-1699",
        "title": "",
        "has_content_in_snapshot": false,
        "hydration_required": true,
        "question_format": "unknown",
        "choice_count": 0
      },
      {
        "index": 5,
        "item_type": "step",
        "step_type": "example",
        "step_id": "453671",
        "content_id": "3864",
        "dom_id": "step-453671",
        "selector": "#step-453671",
        "step_anchor": "step-5",
        "title": "Computing the Tangent or Cotangent of a Quadrantal Angle",
        "key_prerequisites": [
          {
            "topic_id": "299",
            "name": "Multiplying and Dividing With Zero",
            "href": "/topics/299"
          }
        ],
        "has_content_in_snapshot": true
      },
      {
        "index": 6,
        "item_type": "question",
        "question_id": "262382",
        "dom_id": "question-262382",
        "selector": "#question-262382",
        "title": "",
        "has_content_in_snapshot": false,
        "hydration_required": true,
        "question_format": "unknown",
        "choice_count": 0
      },
      {
        "index": 7,
        "item_type": "question",
        "question_id": "262448",
        "dom_id": "question-262448",
        "selector": "#question-262448",
        "title": "",
        "has_content_in_snapshot": false,
        "hydration_required": true,
        "question_format": "unknown",
        "choice_count": 0
      },
      {
        "index": 8,
        "item_type": "question",
        "question_id": "64865",
        "dom_id": "question-64865",
        "selector": "#question-64865",
        "title": "",
        "has_content_in_snapshot": false,
        "hydration_required": true,
        "question_format": "unknown",
        "choice_count": 0
      },
      {
        "index": 9,
        "item_type": "step",
        "step_type": "example",
        "step_id": "453675",
        "content_id": "3865",
        "dom_id": "step-453675",
        "selector": "#step-453675",
        "step_anchor": "step-9",
        "title": "Computing a Reciprocal Ratio of a Quadrantal Angle",
        "key_prerequisites": [
          {
            "topic_id": "611",
            "name": "The Reciprocal Trigonometric Ratios",
            "href": "/topics/611"
          }
        ],
        "has_content_in_snapshot": true
      },
      {
        "index": 10,
        "item_type": "question",
        "question_id": "23417",
        "dom_id": "question-23417",
        "selector": "#question-23417",
        "title": "",
        "has_content_in_snapshot": false,
        "hydration_required": true,
        "question_format": "unknown",
        "choice_count": 0
      },
      {
        "index": 11,
        "item_type": "question",
        "question_id": "246828",
        "dom_id": "question-246828",
        "selector": "#question-246828",
        "title": "",
        "has_content_in_snapshot": false,
        "hydration_required": true,
        "question_format": "unknown",
        "choice_count": 0
      }
    ]
  },
  "capture_targets": {
    "toc": {
      "selector": "#sidebar",
      "filename": "00-TOC.png"
    },
    "lesson_items": [
      {
        "index": 1,
        "item_type": "step",
        "selector": "#step-453667",
        "filename": "01-step-453667.png"
      },
      {
        "index": 2,
        "item_type": "step",
        "selector": "#step-453668",
        "filename": "02-step-453668.png"
      },
      {
        "index": 3,
        "item_type": "question",
        "selector": "#question-262318",
        "filename": "03-question-262318.png"
      },
      {
        "index": 4,
        "item_type": "question",
        "selector": "#question-1699",
        "filename": "04-question-1699.png"
      },
      {
        "index": 5,
        "item_type": "step",
        "selector": "#step-453671",
        "filename": "05-step-453671.png"
      },
      {
        "index": 6,
        "item_type": "question",
        "selector": "#question-262382",
        "filename": "06-question-262382.png"
      },
      {
        "index": 7,
        "item_type": "question",
        "selector": "#question-262448",
        "filename": "07-question-262448.png"
      },
      {
        "index": 8,
        "item_type": "question",
        "selector": "#question-64865",
        "filename": "08-question-64865.png"
      },
      {
        "index": 9,
        "item_type": "step",
        "selector": "#step-453675",
        "filename": "09-step-453675.png"
      },
      {
        "index": 10,
        "item_type": "question",
        "selector": "#question-23417",
        "filename": "10-question-23417.png"
      },
      {
        "index": 11,
        "item_type": "question",
        "selector": "#question-246828",
        "filename": "11-question-246828.png"
      }
    ]
  }
}
