{
  "schema_version": 1,
  "topic_id": "3882",
  "topic_title": "Dividing by 10, 100, and 1,000 Using the Pattern of Zeros",
  "source_html": "/home/jake/Developer/MA/DATA/Topic-HTML/3882.html",
  "source_url": "https://mathacademy.com/topics/3882",
  "toc": {
    "sidebar_selector": "#sidebar",
    "section_links_selector": "#sectionLinks .sectionLink",
    "section_links": [
      {
        "index": 1,
        "step_id": "151573",
        "dom_id": "sectionLink-151573",
        "name": "",
        "title": "Introduction",
        "selector": "#sectionLink-151573"
      },
      {
        "index": 2,
        "step_id": "151574",
        "dom_id": "sectionLink-151574",
        "name": "",
        "title": "Dividing Whole Numbers by Ten",
        "selector": "#sectionLink-151574"
      },
      {
        "index": 3,
        "step_id": "151578",
        "dom_id": "sectionLink-151578",
        "name": "",
        "title": "Dividing Whole Numbers by Ten: Word Problems",
        "selector": "#sectionLink-151578"
      },
      {
        "index": 4,
        "step_id": "151581",
        "dom_id": "sectionLink-151581",
        "name": "",
        "title": "Dividing Whole Numbers by One Hundred and One Thousand",
        "selector": "#sectionLink-151581"
      },
      {
        "index": 5,
        "step_id": "151582",
        "dom_id": "sectionLink-151582",
        "name": "",
        "title": "Dividing Whole Numbers by One Hundred",
        "selector": "#sectionLink-151582"
      },
      {
        "index": 6,
        "step_id": "151585",
        "dom_id": "sectionLink-151585",
        "name": "",
        "title": "Dividing Whole Numbers by One Thousand",
        "selector": "#sectionLink-151585"
      }
    ],
    "topic_prerequisites": [
      {
        "topic_id": "2338",
        "name": "Multiplying by 10, 100, and 1,000 Using the Pattern of Zeros",
        "href": "/topics/multiplying-by-10-100-and-1-000-using-the-pattern-of-zeros-2338"
      },
      {
        "topic_id": "3877",
        "name": "The Relationship Between Multiplication and Division",
        "href": "/topics/the-relationship-between-multiplication-and-division-3877"
      }
    ]
  },
  "lesson": {
    "container_selector": "#lessonContent",
    "item_count": 15,
    "items": [
      {
        "index": 1,
        "item_type": "step",
        "step_type": "tutorial",
        "step_id": "151573",
        "content_id": "8477",
        "dom_id": "step-151573",
        "selector": "#step-151573",
        "step_anchor": "step-1",
        "title": "Introduction",
        "key_prerequisites": [],
        "has_content_in_snapshot": true
      },
      {
        "index": 2,
        "item_type": "step",
        "step_type": "example",
        "step_id": "151574",
        "content_id": "13552",
        "dom_id": "step-151574",
        "selector": "#step-151574",
        "step_anchor": "step-2",
        "title": "Dividing Whole Numbers by Ten",
        "key_prerequisites": [
          {
            "topic_id": "2338",
            "name": "Multiplying by 10, 100, and 1,000 Using the Pattern of Zeros",
            "href": "/topics/2338"
          }
        ],
        "has_content_in_snapshot": true
      },
      {
        "index": 3,
        "item_type": "question",
        "question_id": "172724",
        "dom_id": "question-172724",
        "selector": "#question-172724",
        "title": "",
        "has_content_in_snapshot": false,
        "hydration_required": true,
        "question_format": "unknown",
        "choice_count": 0
      },
      {
        "index": 4,
        "item_type": "question",
        "question_id": "150091",
        "dom_id": "question-150091",
        "selector": "#question-150091",
        "title": "",
        "has_content_in_snapshot": false,
        "hydration_required": true,
        "question_format": "unknown",
        "choice_count": 0
      },
      {
        "index": 5,
        "item_type": "question",
        "question_id": "190827",
        "dom_id": "question-190827",
        "selector": "#question-190827",
        "title": "",
        "has_content_in_snapshot": false,
        "hydration_required": true,
        "question_format": "unknown",
        "choice_count": 0
      },
      {
        "index": 6,
        "item_type": "step",
        "step_type": "example",
        "step_id": "151578",
        "content_id": "13553",
        "dom_id": "step-151578",
        "selector": "#step-151578",
        "step_anchor": "step-6",
        "title": "Dividing Whole Numbers by Ten: Word Problems",
        "key_prerequisites": [],
        "has_content_in_snapshot": true
      },
      {
        "index": 7,
        "item_type": "question",
        "question_id": "150064",
        "dom_id": "question-150064",
        "selector": "#question-150064",
        "title": "",
        "has_content_in_snapshot": false,
        "hydration_required": true,
        "question_format": "unknown",
        "choice_count": 0
      },
      {
        "index": 8,
        "item_type": "question",
        "question_id": "150138",
        "dom_id": "question-150138",
        "selector": "#question-150138",
        "title": "",
        "has_content_in_snapshot": false,
        "hydration_required": true,
        "question_format": "unknown",
        "choice_count": 0
      },
      {
        "index": 9,
        "item_type": "step",
        "step_type": "tutorial",
        "step_id": "151581",
        "content_id": "8479",
        "dom_id": "step-151581",
        "selector": "#step-151581",
        "step_anchor": "step-9",
        "title": "Dividing Whole Numbers by One Hundred and One Thousand",
        "key_prerequisites": [],
        "has_content_in_snapshot": true
      },
      {
        "index": 10,
        "item_type": "step",
        "step_type": "example",
        "step_id": "151582",
        "content_id": "13555",
        "dom_id": "step-151582",
        "selector": "#step-151582",
        "step_anchor": "step-10",
        "title": "Dividing Whole Numbers by One Hundred",
        "key_prerequisites": [],
        "has_content_in_snapshot": true
      },
      {
        "index": 11,
        "item_type": "question",
        "question_id": "150199",
        "dom_id": "question-150199",
        "selector": "#question-150199",
        "title": "",
        "has_content_in_snapshot": false,
        "hydration_required": true,
        "question_format": "unknown",
        "choice_count": 0
      },
      {
        "index": 12,
        "item_type": "question",
        "question_id": "150204",
        "dom_id": "question-150204",
        "selector": "#question-150204",
        "title": "",
        "has_content_in_snapshot": false,
        "hydration_required": true,
        "question_format": "unknown",
        "choice_count": 0
      },
      {
        "index": 13,
        "item_type": "step",
        "step_type": "example",
        "step_id": "151585",
        "content_id": "13557",
        "dom_id": "step-151585",
        "selector": "#step-151585",
        "step_anchor": "step-13",
        "title": "Dividing Whole Numbers by One Thousand",
        "key_prerequisites": [],
        "has_content_in_snapshot": true
      },
      {
        "index": 14,
        "item_type": "question",
        "question_id": "149972",
        "dom_id": "question-149972",
        "selector": "#question-149972",
        "title": "",
        "has_content_in_snapshot": false,
        "hydration_required": true,
        "question_format": "unknown",
        "choice_count": 0
      },
      {
        "index": 15,
        "item_type": "question",
        "question_id": "149974",
        "dom_id": "question-149974",
        "selector": "#question-149974",
        "title": "",
        "has_content_in_snapshot": false,
        "hydration_required": true,
        "question_format": "unknown",
        "choice_count": 0
      }
    ]
  },
  "capture_targets": {
    "toc": {
      "selector": "#sidebar",
      "filename": "00-TOC.png"
    },
    "lesson_items": [
      {
        "index": 1,
        "item_type": "step",
        "selector": "#step-151573",
        "filename": "01-step-151573.png"
      },
      {
        "index": 2,
        "item_type": "step",
        "selector": "#step-151574",
        "filename": "02-step-151574.png"
      },
      {
        "index": 3,
        "item_type": "question",
        "selector": "#question-172724",
        "filename": "03-question-172724.png"
      },
      {
        "index": 4,
        "item_type": "question",
        "selector": "#question-150091",
        "filename": "04-question-150091.png"
      },
      {
        "index": 5,
        "item_type": "question",
        "selector": "#question-190827",
        "filename": "05-question-190827.png"
      },
      {
        "index": 6,
        "item_type": "step",
        "selector": "#step-151578",
        "filename": "06-step-151578.png"
      },
      {
        "index": 7,
        "item_type": "question",
        "selector": "#question-150064",
        "filename": "07-question-150064.png"
      },
      {
        "index": 8,
        "item_type": "question",
        "selector": "#question-150138",
        "filename": "08-question-150138.png"
      },
      {
        "index": 9,
        "item_type": "step",
        "selector": "#step-151581",
        "filename": "09-step-151581.png"
      },
      {
        "index": 10,
        "item_type": "step",
        "selector": "#step-151582",
        "filename": "10-step-151582.png"
      },
      {
        "index": 11,
        "item_type": "question",
        "selector": "#question-150199",
        "filename": "11-question-150199.png"
      },
      {
        "index": 12,
        "item_type": "question",
        "selector": "#question-150204",
        "filename": "12-question-150204.png"
      },
      {
        "index": 13,
        "item_type": "step",
        "selector": "#step-151585",
        "filename": "13-step-151585.png"
      },
      {
        "index": 14,
        "item_type": "question",
        "selector": "#question-149972",
        "filename": "14-question-149972.png"
      },
      {
        "index": 15,
        "item_type": "question",
        "selector": "#question-149974",
        "filename": "15-question-149974.png"
      }
    ]
  }
}
