{
  "image_count": 6,
  "images": [
    {
      "bytes": 13306,
      "content_type": "image/png",
      "filename": "201ea211d60d0c1ad5562d6680badb3e.png",
      "final_url": "https://mathacademy.com/graphics/201ea211d60d0c1ad5562d6680badb3e",
      "img_src": "/graphics/201ea211d60d0c1ad5562d6680badb3e",
      "status": "downloaded"
    },
    {
      "bytes": 8706,
      "content_type": "image/png",
      "filename": "7a7b566a9bc20a63de1cb5e29e9a5c30.png",
      "final_url": "https://mathacademy.com/graphics/7a7b566a9bc20a63de1cb5e29e9a5c30",
      "img_src": "/graphics/7a7b566a9bc20a63de1cb5e29e9a5c30",
      "status": "downloaded"
    },
    {
      "bytes": 14617,
      "content_type": "image/png",
      "filename": "d67fb9c6a43c0d5100ffe8818b747f5c.png",
      "final_url": "https://mathacademy.com/graphics/d67fb9c6a43c0d5100ffe8818b747f5c",
      "img_src": "/graphics/d67fb9c6a43c0d5100ffe8818b747f5c",
      "status": "downloaded"
    },
    {
      "bytes": 30646,
      "content_type": "image/png",
      "filename": "q-161439.png",
      "final_url": "https://mathacademy.com/graphics/q-161439",
      "img_src": "/graphics/q-161439",
      "status": "downloaded"
    },
    {
      "bytes": 26207,
      "content_type": "image/png",
      "filename": "q-162216.png",
      "final_url": "https://mathacademy.com/graphics/q-162216",
      "img_src": "/graphics/q-162216",
      "status": "downloaded"
    },
    {
      "bytes": 16508,
      "content_type": "image/png",
      "filename": "q-162218.png",
      "final_url": "https://mathacademy.com/graphics/q-162218",
      "img_src": "/graphics/q-162218",
      "status": "downloaded"
    }
  ],
  "topic_id": "4160"
}
